django_markup_deprecated-0.0.2.dist-info/DESCRIPTION.rst
django_markup_deprecated-0.0.2.dist-info/METADATA
django_markup_deprecated-0.0.2.dist-info/pydist.json
django_markup_deprecated-0.0.2.dist-info/RECORD
django_markup_deprecated-0.0.2.dist-info/top_level.txt
django_markup_deprecated-0.0.2.dist-info/WHEEL
markup_deprecated/__init__.py
markup_deprecated/models.py
markup_deprecated/tests.py
markup_deprecated/templatetags/__init__.py
markup_deprecated/templatetags/markup.py
