Metadata-Version: 2.0
Name: django-markup-deprecated
Version: 0.0.2
Summary: Original django.contrib.markup from Django 1.4.1.
Home-page: https://github.com/fcurella/django-markup-deprecated
Author: Flavio Curella
Author-email: flavio.curella@gmail.com
License: BSD
Platform: UNKNOWN
Classifier: Development Status :: 7 - Inactive
Classifier: Environment :: Web Environment
Classifier: Framework :: Django
Classifier: Intended Audience :: Developers
Classifier: License :: OSI Approved :: BSD License
Classifier: Operating System :: OS Independent
Classifier: Programming Language :: Python
